Hlo123/__init__.py
hlo123-0.1.0.dist-info/licenses/LICENSE
hlo123-0.1.0.dist-info/METADATA
hlo123-0.1.0.dist-info/WHEEL
hlo123-0.1.0.dist-info/top_level.txt
hlo123-0.1.0.dist-info/RECORD
